blink2png_bridge/__init__.py
blink2png_bridge-0.1.4.dist-info/LICENSE
blink2png_bridge-0.1.4.dist-info/METADATA
blink2png_bridge-0.1.4.dist-info/WHEEL
blink2png_bridge-0.1.4.dist-info/top_level.txt
blink2png_bridge-0.1.4.dist-info/zip-safe
blink2png_bridge-0.1.4.dist-info/RECORD
